Topsis_Bhavya_101903365/__init__.py
Topsis_Bhavya_101903365-1.0.1.dist-info/LICENSE.txt
Topsis_Bhavya_101903365-1.0.1.dist-info/METADATA
Topsis_Bhavya_101903365-1.0.1.dist-info/WHEEL
Topsis_Bhavya_101903365-1.0.1.dist-info/top_level.txt
Topsis_Bhavya_101903365-1.0.1.dist-info/RECORD
