Metadata-Version: 2.1
Name: Topsis-Bhavya-101903365
Version: 1.0.1
Summary: A Python package implementing TOPSIS technique.
Home-page: UNKNOWN
Author: Bhavya Kakwani
Author-email: bhavyakakwani@gmail.com
License: MIT
Platform: UNKNOWN
Classifier: License :: OSI Approved :: MIT License
Classifier: Programming Language :: Python :: 3
Classifier: Programming Language :: Python :: 3.8
Requires-Dist: pandas
